dsharp_opac-1.1.13.dist-info/METADATA
dsharp_opac-1.1.13.dist-info/WHEEL
dsharp_opac-1.1.13.dist-info/LICENSE
dsharp_opac/bhmie_fortran.cpython-313-darwin.so
dsharp_opac/fit_module.cpython-313-darwin.so
dsharp_opac/__init__.py
dsharp_opac/bhmie_python.py
dsharp_opac/dsharp_opac.py
dsharp_opac/data/andrews2009.dat
dsharp_opac/data/default_opacities_extrapol.npz
dsharp_opac/data/default_opacities_smooth.npz
dsharp_opac/data/default_opacities.npz
dsharp_opac/data/icefree_opacities_smooth.npz
dsharp_opac/data/icefree_opacities.npz
dsharp_opac/data/kappa_D01_T100K_p3.5_amax1mm.csv
dsharp_opac/data/kataoka_mix.lnk
dsharp_opac/data/Kataoka2014-Fig2b-1e-5cm.csv
dsharp_opac/data/Kataoka2014-Fig2d-1e-5cm.csv
dsharp_opac/data/ricci_compact.npz
dsharp_opac/optical_constants/draine/links.json
dsharp_opac/optical_constants/henning/new/links.json
dsharp_opac/optical_constants/henning/old/links.json
dsharp_opac/optical_constants/jaeger/links.json
dsharp_opac/optical_constants/luca/aC_ACH2_Zubko.dat
dsharp_opac/optical_constants/luca/H2Oice_Warren.dat
dsharp_opac/optical_constants/luca/silicate.dat
dsharp_opac/optical_constants/pollack1994/make_lnk.py
dsharp_opac/optical_constants/pollack1994/P94-iron-k.csv
dsharp_opac/optical_constants/pollack1994/P94-iron-n.csv
dsharp_opac/optical_constants/pollack1994/P94-iron.lnk
dsharp_opac/optical_constants/pollack1994/P94-olivine-k.csv
dsharp_opac/optical_constants/pollack1994/P94-olivine-n.csv
dsharp_opac/optical_constants/pollack1994/P94-olivine.lnk
dsharp_opac/optical_constants/pollack1994/P94-organics-k.csv
dsharp_opac/optical_constants/pollack1994/P94-organics-n.csv
dsharp_opac/optical_constants/pollack1994/P94-organics.lnk
dsharp_opac/optical_constants/pollack1994/P94-orthopyroxene-k.csv
dsharp_opac/optical_constants/pollack1994/P94-orthopyroxene-n.csv
dsharp_opac/optical_constants/pollack1994/P94-orthopyroxene.lnk
dsharp_opac/optical_constants/pollack1994/P94-troilite-k.csv
dsharp_opac/optical_constants/pollack1994/P94-troilite-n.csv
dsharp_opac/optical_constants/pollack1994/P94-troilite.lnk
dsharp_opac-1.1.13.dist-info/RECORD
