Metadata-Version: 2.1
Name: dsharp_opac
Version: 1.1.13
Summary: python routines to calculate mie opacities
Author-Email: Til Birnstiel & DSHARP collaboration <til.birnstiel@lmu.de>
License:                     GNU GENERAL PUBLIC LICENSE
Project-URL: Repository, https://github.com/birnstiel/dsharp_opac/
Requires-Dist: numpy
Requires-Dist: scipy
Requires-Dist: matplotlib
Requires-Dist: astropy
Requires-Dist: mpmath
Requires-Dist: setuptools
